pywordfreq-0.4.2.dist-info/METADATA
pywordfreq-0.4.2.dist-info/WHEEL
pywordfreq/pywordfreq.pyi
pywordfreq/word_frequencies.gz
pywordfreq/__init__.py
pywordfreq/pywordfreq.cpython-311-x86_64-linux-gnu.so
pywordfreq-0.4.2.dist-info/RECORD
