Metadata-Version: 2.1
Name: pywordfreq
Version: 0.4.2
Summary: Word frequency checker based on Wikipedia corpus written in Rust
Keywords: word,frequency,frequencies,rust,pyo3
Home-Page: https://github.com/intsights/pywordfreq
Author: Gal Ben David <gal@intsights.com>
Author-email: Gal Ben David <gal@intsights.com>
License: MIT
Project-URL: Source Code, https://github.com/intsights/pywordfreq
